upytl/__init__.py
upytl/bulma.py
upytl/core.py
upytl/helpers.py
upytl/html.py
upytl/xtemplate.py
upytl-0.0.9.dist-info/LICENSE
upytl-0.0.9.dist-info/METADATA
upytl-0.0.9.dist-info/WHEEL
upytl-0.0.9.dist-info/top_level.txt
upytl-0.0.9.dist-info/RECORD
