Metadata-Version: 2.1
Name: upytl
Version: 0.0.9
Summary: UPYTL - Ultra Pythonic Template Language
Author-email: Valery Kucherov <valq7711@gmail.com>
License: MIT License
Project-URL: homepage, https://github.com/valq7711/upytl
Project-URL: repository, https://github.com/valq7711/upytl
Keywords: python,webapplication,html,template
Classifier: Development Status :: 4 - Beta
Classifier: Environment :: Web Environment
Classifier: Intended Audience :: Developers
Classifier: License :: OSI Approved :: MIT License
Classifier: Operating System :: OS Independent
Classifier: Programming Language :: Python :: 3.7
Classifier: Programming Language :: Python :: 3.8
Classifier: Programming Language :: Python :: 3.9
Classifier: Programming Language :: Python :: 3.10
Classifier: Programming Language :: Python :: 3.11
Classifier: Topic :: Internet :: WWW/HTTP :: HTTP Servers
Classifier: Topic :: Software Development :: Libraries :: Python Modules
Classifier: Topic :: Text Processing :: Markup :: HTML
Requires-Python: >=3.7
License-File: LICENSE
